crongit/__init__.py
crongit/cli_app.py
crongit/cli_output.py
crongit/client.py
crongit/commands.py
crongit/dotfile.py
crongit/main.py
crongit/scheduler.py
crongit/server_handler.py
crongit-0.1.dist-info/METADATA
crongit-0.1.dist-info/WHEEL
crongit-0.1.dist-info/entry_points.txt
crongit-0.1.dist-info/top_level.txt
crongit-0.1.dist-info/RECORD
